subclass_getter/__init__.py
subclass_getter/get_subclasses.py
subclass_getter/py.typed
subclass_getter-0.1.3.dist-info/METADATA
subclass_getter-0.1.3.dist-info/WHEEL
subclass_getter-0.1.3.dist-info/licenses/LICENSE
subclass_getter-0.1.3.dist-info/RECORD
