Metadata-Version: 2.4
Name: subclass-getter
Version: 0.1.3
Summary: Gets subclasses of a class recursively
Project-URL: Homepage, https://pypi.org/project/subclass-getter/
Project-URL: Repository, https://github.com/Tesla2000/subclass-getter
Project-URL: Issues, https://github.com/Tesla2000/subclass-getter/issues
Author-email: Tesla2000 <fratajczak124@gmail.com>
License: MIT License
License-File: LICENSE
Keywords: inheritance,introspection,subclasses
Classifier: Development Status :: 3 - Alpha
Classifier: License :: OSI Approved :: MIT License
Classifier: Programming Language :: Python :: 3
Classifier: Programming Language :: Python :: 3 :: Only
Classifier: Programming Language :: Python :: 3.9
Classifier: Programming Language :: Python :: 3.10
Classifier: Programming Language :: Python :: 3.11
Classifier: Programming Language :: Python :: 3.12
Classifier: Typing :: Typed
Requires-Python: >=3.9
